xe_likelihood/__init__.py
xe_likelihood/binwise_inference.py
xe_likelihood/cli.py
xe_likelihood/data/__init__.py
xe_likelihood/data/ancillary_data/__init__.py
xe_likelihood/data/ancillary_data/dRdE_wimp_SI_50GeV_10-45.csv
xe_likelihood/data/ancillary_data/dRdE_wimp_pion_100GeV_10-45.csv
xe_likelihood/data/ancillary_data/xenon1t_1ty.csv
xe_likelihood/data/ancillary_data/xenonnt_projection_SI_20ty.csv
xe_likelihood/data/xe1t_nr_1ty_result/XENON1T_binwise_NR_LL.json
xe_likelihood/data/xe1t_nr_1ty_result/XENON1T_binwise_NR_MM.json
xe_likelihood/data/xe1t_nr_1ty_result/__init__.py
xe_likelihood/data/xe1t_nr_1ty_result/threshold_using_lines_90pct.json
xe_likelihood/data/xent_nr_20ty_projection/XENONnT_binwise_NR_LL_toyMC.json.gz
xe_likelihood/data/xent_nr_20ty_projection/XENONnT_binwise_NR_MM.json
xe_likelihood/data/xent_nr_20ty_projection/__init__.py
xe_likelihood/demo.py
xe_likelihood/hist2d.py
xe_likelihood/spectrum.py
xe_likelihood-0.1.0.dist-info/LICENSE
xe_likelihood-0.1.0.dist-info/METADATA
xe_likelihood-0.1.0.dist-info/WHEEL
xe_likelihood-0.1.0.dist-info/entry_points.txt
xe_likelihood-0.1.0.dist-info/RECORD
