Metadata-Version: 2.1
Name: xe-likelihood
Version: 0.1.0
Summary: Binwise approximate inference for XENON1T and XENONnT experiments.
Home-page: https://github.com/XENON1T/xe_likelihood
License: MIT
Author: XENON collaboration
Author-email: knut.dundas.moraa@columbia.edu
Requires-Python: >=3.7.1,<4.0.0
Classifier: Development Status :: 2 - Pre-Alpha
Classifier: Intended Audience :: Developers
Classifier: License :: OSI Approved :: MIT License
Classifier: Natural Language :: English
Classifier: Programming Language :: Python :: 3
Classifier: Programming Language :: Python :: 3.8
Classifier: Programming Language :: Python :: 3.9
Classifier: Programming Language :: Python :: 3.10
Classifier: Programming Language :: Python :: 3.11
Classifier: Programming Language :: Python :: 3.7
Provides-Extra: wimps
Requires-Dist: click (>=8.0.3,<9.0.0)
Requires-Dist: matplotlib
Requires-Dist: numpy
Requires-Dist: pandas (!=1.3.4)
Requires-Dist: scipy
Requires-Dist: tqdm
Requires-Dist: wimprates (>=0.3.2,<0.4.0) ; extra == "wimps"
